{
  "metric": "visqol",
  "reference_dir": "/orange/ufdatastudios/c.okocha/Dataset/afrispeech_multilingual_wav",
  "degraded_dir": "/orange/ufdatastudios/c.okocha/CodecEval-Africa/outputs/afrispeech_multilingual/FocalCodec_outputs/focalcodec_50hz_2k_causal",
  "num_ref_files": 100,
  "num_deg_files": 100,
  "num_scored_files": 100,
  "moslqo": 4.776192258340014,
  "moslqo_std": 0.07536206334056748,
  "moslqo_min": 4.4812732606951435,
  "moslqo_max": 4.95289284837099,
  "per_file": [
    {
      "filename": "common_voice_ig_30477016.wav",
      "moslqo": 4.878376745463394,
      "similarity": 0.526864327275856,
      "degradation": 0.2540507860778345
    },
    {
      "filename": "common_voice_ig_30477017.wav",
      "moslqo": 4.748067302145307,
      "similarity": 0.42998764299740316,
      "degradation": 0.12077950323980846
    },
    {
      "filename": "common_voice_ig_30477018.wav",
      "moslqo": 4.780896613378393,
      "similarity": 0.47547553713052926,
      "degradation": 0.18998436932953833
    },
    {
      "filename": "common_voice_ig_30477019.wav",
      "moslqo": 4.737008417675387,
      "similarity": 0.4791171862332692,
      "degradation": 0.19540695320959622
    },
    {
      "filename": "common_voice_ig_30477020.wav",
      "moslqo": 4.73157128168671,
      "similarity": 0.5924070051135467,
      "degradation": 0.2700245319014767
    },
    {
      "filename": "common_voice_ig_30689626.wav",
      "moslqo": 4.837700643873951,
      "similarity": 0.4432778119486333,
      "degradation": 0.13336836527864715
    },
    {
      "filename": "common_voice_ig_30689627.wav",
      "moslqo": 4.806175329474621,
      "similarity": 0.40275052623575874,
      "degradation": 0.09088851987223134
    },
    {
      "filename": "common_voice_ig_30689628.wav",
      "moslqo": 4.852880713187683,
      "similarity": 0.6764032054837394,
      "degradation": 0.10458715170373556
    },
    {
      "filename": "common_voice_ig_30689629.wav",
      "moslqo": 4.785465831120613,
      "similarity": 0.12249362862801648,
      "degradation": 0.13349380276857548
    },
    {
      "filename": "common_voice_ig_30689630.wav",
      "moslqo": 4.787526036292345,
      "similarity": 0.4728619371249223,
      "degradation": 0.16018474087779622
    },
    {
      "filename": "common_voice_ig_30689631.wav",
      "moslqo": 4.7294856253128845,
      "similarity": 0.4998039244402832,
      "degradation": 0.10545596167745042
    },
    {
      "filename": "common_voice_ig_30689632.wav",
      "moslqo": 4.690385428321312,
      "similarity": 0.2928244493720796,
      "degradation": 0.10008202117799314
    },
    {
      "filename": "common_voice_ig_30689633.wav",
      "moslqo": 4.742060673371088,
      "similarity": 0.5648972165426084,
      "degradation": 0.08517001416348291
    },
    {
      "filename": "common_voice_ig_30689634.wav",
      "moslqo": 4.7733740754982374,
      "similarity": 0.4277252519903488,
      "degradation": 0.16200855317757523
    },
    {
      "filename": "common_voice_ig_30689635.wav",
      "moslqo": 4.780259763721526,
      "similarity": 0.26029466351857866,
      "degradation": 0.1941412331172132
    },
    {
      "filename": "common_voice_ig_30689652.wav",
      "moslqo": 4.770024399403694,
      "similarity": 0.4521316582525278,
      "degradation": 0.12715434660651082
    },
    {
      "filename": "common_voice_ig_30689655.wav",
      "moslqo": 4.7470969783443415,
      "similarity": 0.4843556573492941,
      "degradation": 0.12074376320707736
    },
    {
      "filename": "common_voice_ig_30689656.wav",
      "moslqo": 4.70135322283016,
      "similarity": 0.307500017747982,
      "degradation": 0.10978766222295022
    },
    {
      "filename": "common_voice_ig_30689657.wav",
      "moslqo": 4.805744707030124,
      "similarity": 0.3601444238130292,
      "degradation": 0.17787467478439667
    },
    {
      "filename": "common_voice_ig_30689658.wav",
      "moslqo": 4.781650581319432,
      "similarity": 0.6302078749889806,
      "degradation": 0.09624128027863943
    },
    {
      "filename": "common_voice_ig_30689665.wav",
      "moslqo": 4.725471043828729,
      "similarity": 0.33851957257421894,
      "degradation": 0.32707539558372245
    },
    {
      "filename": "common_voice_ig_30689666.wav",
      "moslqo": 4.715491157737474,
      "similarity": 0.28976528850857697,
      "degradation": 0.17093290633491587
    },
    {
      "filename": "common_voice_ig_30689667.wav",
      "moslqo": 4.817529267550345,
      "similarity": 0.42447108819627477,
      "degradation": 0.16610910369434406
    },
    {
      "filename": "common_voice_ig_30689668.wav",
      "moslqo": 4.798874564402629,
      "similarity": 0.6316374174027138,
      "degradation": 0.2110942805364493
    },
    {
      "filename": "common_voice_ig_30689669.wav",
      "moslqo": 4.837987466276806,
      "similarity": 0.3525861316914577,
      "degradation": 0.24438641383520188
    },
    {
      "filename": "common_voice_ig_30689997.wav",
      "moslqo": 4.768655085712668,
      "similarity": 0.5224042125958411,
      "degradation": 0.10928856461579273
    },
    {
      "filename": "common_voice_ig_30689998.wav",
      "moslqo": 4.9021115378022095,
      "similarity": 0.2546639904602056,
      "degradation": 0.12712962263560867
    },
    {
      "filename": "common_voice_ig_30689999.wav",
      "moslqo": 4.779281484096381,
      "similarity": 0.5385259396371438,
      "degradation": 0.41170708296524694
    },
    {
      "filename": "common_voice_ig_30690000.wav",
      "moslqo": 4.764540746285803,
      "similarity": 0.17132733506420375,
      "degradation": 0.2991559212404802
    },
    {
      "filename": "common_voice_ig_30690001.wav",
      "moslqo": 4.848197786660039,
      "similarity": 0.5372151045846805,
      "degradation": 0.19977621625501096
    },
    {
      "filename": "common_voice_ig_30690008.wav",
      "moslqo": 4.7704382406924575,
      "similarity": 0.6175006147496525,
      "degradation": 0.17983184420155107
    },
    {
      "filename": "common_voice_ig_30690009.wav",
      "moslqo": 4.784994683722559,
      "similarity": 0.5873835597443616,
      "degradation": 0.25800805556823714
    },
    {
      "filename": "common_voice_ig_30690010.wav",
      "moslqo": 4.753470882116114,
      "similarity": 0.5626600670690028,
      "degradation": 0.12708590935514352
    },
    {
      "filename": "common_voice_ig_30690011.wav",
      "moslqo": 4.4812732606951435,
      "similarity": 0.49062827518649615,
      "degradation": 0.11105148178158164
    },
    {
      "filename": "common_voice_ig_30690012.wav",
      "moslqo": 4.733870563562651,
      "similarity": 0.4323265970401026,
      "degradation": 0.1513953015776205
    },
    {
      "filename": "common_voice_ig_30690129.wav",
      "moslqo": 4.662237006314706,
      "similarity": 0.42693795080435853,
      "degradation": 0.11364801738639696
    },
    {
      "filename": "common_voice_ig_30690130.wav",
      "moslqo": 4.812465748741091,
      "similarity": 0.3307362278989068,
      "degradation": 0.24049931508835765
    },
    {
      "filename": "common_voice_ig_30690131.wav",
      "moslqo": 4.676957792607894,
      "similarity": 0.5407148847769929,
      "degradation": 0.19490263882350822
    },
    {
      "filename": "common_voice_ig_30690132.wav",
      "moslqo": 4.692069622451347,
      "similarity": 0.4323285754726883,
      "degradation": 0.15637869227310808
    },
    {
      "filename": "common_voice_ig_30690133.wav",
      "moslqo": 4.668462601637666,
      "similarity": 0.3940246977237551,
      "degradation": 0.16906835922122687
    },
    {
      "filename": "common_voice_ig_30690252.wav",
      "moslqo": 4.734676044433901,
      "similarity": 0.5208571895380287,
      "degradation": 0.24424014661175664
    },
    {
      "filename": "common_voice_ig_30690253.wav",
      "moslqo": 4.759425708131419,
      "similarity": 0.5287542287811626,
      "degradation": 0.23055835920489942
    },
    {
      "filename": "common_voice_ig_30690254.wav",
      "moslqo": 4.715259489802232,
      "similarity": 0.5867084648284682,
      "degradation": 0.3021678478430403
    },
    {
      "filename": "common_voice_ig_30690255.wav",
      "moslqo": 4.756255136652479,
      "similarity": 0.5276667962670745,
      "degradation": 0.3376221117238817
    },
    {
      "filename": "common_voice_ig_30690256.wav",
      "moslqo": 4.709864435330126,
      "similarity": 0.5051837236402902,
      "degradation": 0.2742316732456953
    },
    {
      "filename": "common_voice_ig_30690342.wav",
      "moslqo": 4.811337094376376,
      "similarity": 0.5722705694003265,
      "degradation": 0.15211753112254278
    },
    {
      "filename": "common_voice_ig_30690343.wav",
      "moslqo": 4.6291192924701505,
      "similarity": 0.4855109899451341,
      "degradation": 0.09239928472274728
    },
    {
      "filename": "common_voice_ig_30690344.wav",
      "moslqo": 4.762269224980396,
      "similarity": 0.5477311256677693,
      "degradation": 0.22624558409368722
    },
    {
      "filename": "common_voice_ig_30690345.wav",
      "moslqo": 4.7804610650250385,
      "similarity": 0.6078476114955834,
      "degradation": 0.27678264816013
    },
    {
      "filename": "common_voice_ig_30690346.wav",
      "moslqo": 4.766962534229789,
      "similarity": 0.4818844280703959,
      "degradation": 0.24862333363821343
    },
    {
      "filename": "common_voice_ig_30690397.wav",
      "moslqo": 4.754389005682665,
      "similarity": 0.4475204857955049,
      "degradation": 0.20115020292327102
    },
    {
      "filename": "common_voice_ig_30690398.wav",
      "moslqo": 4.667343598968689,
      "similarity": 0.35259022449522237,
      "degradation": 0.22918177900947467
    },
    {
      "filename": "common_voice_ig_30690399.wav",
      "moslqo": 4.799334494965208,
      "similarity": 0.5056386063943107,
      "degradation": 0.25065329211337406
    },
    {
      "filename": "common_voice_ig_30690400.wav",
      "moslqo": 4.781495304893319,
      "similarity": 0.593722875236477,
      "degradation": 0.22660181401150692
    },
    {
      "filename": "common_voice_ig_30690401.wav",
      "moslqo": 4.766196518533431,
      "similarity": 0.5184464732888288,
      "degradation": 0.23083150545340914
    },
    {
      "filename": "common_voice_ig_30690501.wav",
      "moslqo": 4.683489561357049,
      "similarity": 0.4531256257053164,
      "degradation": 0.17959557190010222
    },
    {
      "filename": "common_voice_ig_30690502.wav",
      "moslqo": 4.889473022254064,
      "similarity": 0.4809653813827983,
      "degradation": 0.11088615001148483
    },
    {
      "filename": "common_voice_ig_30690503.wav",
      "moslqo": 4.5727507225144075,
      "similarity": 0.6420764014172906,
      "degradation": 0.21842640153401327
    },
    {
      "filename": "common_voice_ig_30690504.wav",
      "moslqo": 4.713932789788607,
      "similarity": 0.26234973626361124,
      "degradation": 0.25672213391051946
    },
    {
      "filename": "common_voice_ig_30690505.wav",
      "moslqo": 4.737608951400313,
      "similarity": 0.38685220179316093,
      "degradation": 0.1747356801221649
    },
    {
      "filename": "common_voice_ig_30690536.wav",
      "moslqo": 4.711218199759868,
      "similarity": 0.16993603205492316,
      "degradation": 0.3172096924833052
    },
    {
      "filename": "common_voice_ig_30690537.wav",
      "moslqo": 4.778985210106461,
      "similarity": 0.503715577392292,
      "degradation": 0.20031316852860093
    },
    {
      "filename": "common_voice_ig_30690538.wav",
      "moslqo": 4.768546830770923,
      "similarity": 0.5792201088077938,
      "degradation": 0.252119983956282
    },
    {
      "filename": "common_voice_ig_30690539.wav",
      "moslqo": 4.734461560684015,
      "similarity": 0.5705860320594301,
      "degradation": 0.2692042148113887
    },
    {
      "filename": "common_voice_ig_30690540.wav",
      "moslqo": 4.7724750163875935,
      "similarity": 0.4536403813457277,
      "degradation": 0.1927939531502818
    },
    {
      "filename": "common_voice_ig_30690541.wav",
      "moslqo": 4.8202075635284345,
      "similarity": 0.15456328279426884,
      "degradation": 0.28626742858085086
    },
    {
      "filename": "common_voice_ig_30690542.wav",
      "moslqo": 4.95289284837099,
      "similarity": 0.4452755057933545,
      "degradation": 0.31708194272173884
    },
    {
      "filename": "common_voice_ig_30690543.wav",
      "moslqo": 4.876660144903589,
      "similarity": 0.4096009005061702,
      "degradation": 0.2736686762751297
    },
    {
      "filename": "common_voice_ig_30690544.wav",
      "moslqo": 4.852795906556245,
      "similarity": 0.30575015603663547,
      "degradation": 0.3128206869691855
    },
    {
      "filename": "common_voice_ig_30690545.wav",
      "moslqo": 4.691403361645341,
      "similarity": 0.3519151023384639,
      "degradation": 0.14708371504925388
    },
    {
      "filename": "common_voice_ig_30690546.wav",
      "moslqo": 4.840519989907239,
      "similarity": 0.2853405901080276,
      "degradation": 0.12630694395754782
    },
    {
      "filename": "common_voice_ig_30690547.wav",
      "moslqo": 4.68690794958834,
      "similarity": 0.5278762103504936,
      "degradation": 0.1677840728513359
    },
    {
      "filename": "common_voice_ig_30690548.wav",
      "moslqo": 4.707096815473221,
      "similarity": 0.46360958876499936,
      "degradation": 0.2044043117693538
    },
    {
      "filename": "common_voice_ig_30690549.wav",
      "moslqo": 4.6921249470705755,
      "similarity": 0.391904758993439,
      "degradation": 0.14049595984761343
    },
    {
      "filename": "common_voice_ig_30690566.wav",
      "moslqo": 4.6795365490800895,
      "similarity": 0.4989926128153481,
      "degradation": 0.13745286687292912
    },
    {
      "filename": "common_voice_ig_30690567.wav",
      "moslqo": 4.847234591529798,
      "similarity": 0.279053634357656,
      "degradation": 0.05276636444444538
    },
    {
      "filename": "common_voice_ig_30690568.wav",
      "moslqo": 4.742425442540094,
      "similarity": 0.3863811652043286,
      "degradation": 0.15693106163030668
    },
    {
      "filename": "common_voice_ig_30690569.wav",
      "moslqo": 4.680195540637187,
      "similarity": 0.4814400238061419,
      "degradation": 0.12300005000584169
    },
    {
      "filename": "common_voice_ig_30690570.wav",
      "moslqo": 4.860293356234936,
      "similarity": 0.590837356475772,
      "degradation": 0.06324089604435823
    },
    {
      "filename": "common_voice_ig_43439374.wav",
      "moslqo": 4.865662300809745,
      "similarity": 0.6445633605579115,
      "degradation": 0.06576119770774935
    },
    {
      "filename": "common_voice_ig_43439375.wav",
      "moslqo": 4.81823439816502,
      "similarity": 0.4192799328694234,
      "degradation": 0.12352068796097981
    },
    {
      "filename": "common_voice_ig_43439376.wav",
      "moslqo": 4.867381811653717,
      "similarity": 0.4418902246554581,
      "degradation": 0.08279533392948701
    },
    {
      "filename": "common_voice_ig_43439377.wav",
      "moslqo": 4.771859119667958,
      "similarity": 0.46796734520730243,
      "degradation": 0.009728187207488248
    },
    {
      "filename": "common_voice_ig_43439378.wav",
      "moslqo": 4.863662735726901,
      "similarity": 0.3662629294609679,
      "degradation": 0.04592141023643659
    },
    {
      "filename": "common_voice_ig_43439508.wav",
      "moslqo": 4.830626113916395,
      "similarity": 0.38179510754842494,
      "degradation": 0.04484359696482165
    },
    {
      "filename": "common_voice_ig_43439514.wav",
      "moslqo": 4.885052132079612,
      "similarity": 0.5016096038335447,
      "degradation": 0.15517928980761309
    },
    {
      "filename": "common_voice_ig_43439515.wav",
      "moslqo": 4.858077707066763,
      "similarity": 0.3344653941672181,
      "degradation": 0.045719263301642554
    },
    {
      "filename": "common_voice_ig_43439516.wav",
      "moslqo": 4.872317792169897,
      "similarity": 0.37407277156046603,
      "degradation": 0.038245438280084976
    },
    {
      "filename": "common_voice_ig_43439517.wav",
      "moslqo": 4.72053658465448,
      "similarity": 0.46495865183539387,
      "degradation": 0.05742215071956602
    },
    {
      "filename": "common_voice_ig_43439592.wav",
      "moslqo": 4.794032821646012,
      "similarity": 0.40496578088284507,
      "degradation": 0.05978988760923021
    },
    {
      "filename": "common_voice_ig_43439593.wav",
      "moslqo": 4.884521711164364,
      "similarity": 0.4135066439838113,
      "degradation": 0.13479724087086153
    },
    {
      "filename": "common_voice_ig_43439594.wav",
      "moslqo": 4.890043736377549,
      "similarity": 0.3410937934660231,
      "degradation": 0.04685761173560443
    },
    {
      "filename": "common_voice_ig_43439595.wav",
      "moslqo": 4.855091748248498,
      "similarity": 0.4614313538007276,
      "degradation": 0.09561641979522739
    },
    {
      "filename": "common_voice_ig_43439596.wav",
      "moslqo": 4.84528204053268,
      "similarity": 0.3482735165931618,
      "degradation": 0.022529498323269337
    },
    {
      "filename": "common_voice_ig_43472503.wav",
      "moslqo": 4.882485979854989,
      "similarity": 0.4995128952869966,
      "degradation": 0.12255971232752472
    },
    {
      "filename": "common_voice_ig_43472504.wav",
      "moslqo": 4.793924346060507,
      "similarity": 0.45915543291295113,
      "degradation": 0.19460596980029965
    },
    {
      "filename": "common_voice_ig_43472505.wav",
      "moslqo": 4.852312235734088,
      "similarity": 0.5132170810867579,
      "degradation": 0.14765670738546088
    },
    {
      "filename": "common_voice_ig_43472506.wav",
      "moslqo": 4.8234702662316105,
      "similarity": 0.4155281570245819,
      "degradation": 0.2071743600818512
    },
    {
      "filename": "common_voice_ig_43472507.wav",
      "moslqo": 4.849913878254807,
      "similarity": 0.5345272579820151,
      "degradation": 0.15580235865628844
    },
    {
      "filename": "common_voice_ig_43488897.wav",
      "moslqo": 4.845625641075372,
      "similarity": 0.4971298689876079,
      "degradation": 0.1894146422826497
    }
  ]
}