{
  "metric": "prosody",
  "reference_dir": "/orange/ufdatastudios/c.okocha/CodecEval-Africa/data/afri_names_150_flat",
  "degraded_dir": "/orange/ufdatastudios/c.okocha/CodecEval-Africa/outputs/afrinames/SemantiCodec_outputs/1.40kbps",
  "num_ref_files": 150,
  "num_deg_files": 150,
  "num_scored_files": 150,
  "overall_prosody": 1.62054248563122,
  "overall_prosody_std": 0.3863914517437141,
  "f0_rmse": 4.752235387626784,
  "f0_rmse_std": 1.9757684441183254,
  "per_file": [
    {
      "filename": "akan01.wav",
      "f0_rmse": 4.839642007915738,
      "f0_correlation": 0.405512062217058,
      "tempo_similarity": 1.0,
      "rhythm_similarity": 0.9543566794330992,
      "stress_similarity": 0.964648248349367,
      "overall_prosody": 1.6328317995830524
    },
    {
      "filename": "akan02.wav",
      "f0_rmse": 4.920772573665666,
      "f0_correlation": 0.45788922839903956,
      "tempo_similarity": 1.0,
      "rhythm_similarity": 0.9240117369916456,
      "stress_similarity": 0.9749465150802274,
      "overall_prosody": 1.6555240108273157
    },
    {
      "filename": "akan03.wav",
      "f0_rmse": 3.06613923932049,
      "f0_correlation": 0.6001536635237844,
      "tempo_similarity": 1.0,
      "rhythm_similarity": 0.8870391393413172,
      "stress_similarity": 0.9774915602677923,
      "overall_prosody": 1.3061647204906766
    },
    {
      "filename": "akan04.wav",
      "f0_rmse": 3.2972479133675225,
      "f0_correlation": 0.39689412531797114,
      "tempo_similarity": 1.0,
      "rhythm_similarity": 0.881922364452748,
      "stress_similarity": 0.9797003117802261,
      "overall_prosody": 1.3111529429836934
    },
    {
      "filename": "akan05.wav",
      "f0_rmse": 0.9805859910781793,
      "f0_correlation": 0.856858683660462,
      "tempo_similarity": 0.9375,
      "rhythm_similarity": 0.941407363635427,
      "stress_similarity": 0.9721078855833012,
      "overall_prosody": 0.9376919847914739
    },
    {
      "filename": "akan06.wav",
      "f0_rmse": 4.346903062786733,
      "f0_correlation": 0.1594673574687861,
      "tempo_similarity": 1.0,
      "rhythm_similarity": 0.9424283889017395,
      "stress_similarity": 0.9644705840053316,
      "overall_prosody": 1.4826538786325183
    },
    {
      "filename": "akan07.wav",
      "f0_rmse": 5.307240307066013,
      "f0_correlation": 0.39619829823517627,
      "tempo_similarity": 1.0,
      "rhythm_similarity": 0.9588170907273391,
      "stress_similarity": 0.9724564360971146,
      "overall_prosody": 1.7269424264251285
    },
    {
      "filename": "akan08.wav",
      "f0_rmse": 2.7389208159179477,
      "f0_correlation": 0.546631755664888,
      "tempo_similarity": 1.0,
      "rhythm_similarity": 0.6955390857820976,
      "stress_similarity": 0.9692373606519396,
      "overall_prosody": 1.1900658036033747
    },
    {
      "filename": "akan09.wav",
      "f0_rmse": 4.179119945733848,
      "f0_correlation": 0.6413329884956206,
      "tempo_similarity": 0.6923076923076923,
      "rhythm_similarity": 0.9542236466401107,
      "stress_similarity": 0.974834339824574,
      "overall_prosody": 1.4883637226003692
    },
    {
      "filename": "akan10.wav",
      "f0_rmse": 4.925102543728725,
      "f0_correlation": 0.2714983210673396,
      "tempo_similarity": 0.9473684210526316,
      "rhythm_similarity": 0.9415238092385243,
      "stress_similarity": 0.9752909691038365,
      "overall_prosody": 1.6121568128382116
    },
    {
      "filename": "akan11.wav",
      "f0_rmse": 4.9423545845693075,
      "f0_correlation": 0.17382795850265442,
      "tempo_similarity": 1.0,
      "rhythm_similarity": 0.9671820844137756,
      "stress_similarity": 0.9718505325062858,
      "overall_prosody": 1.6110430319984048
    },
    {
      "filename": "akan12.wav",
      "f0_rmse": 3.5518448251119183,
      "f0_correlation": 0.43024404289498785,
      "tempo_similarity": 1.0,
      "rhythm_similarity": 0.9526615305472925,
      "stress_similarity": 0.9637961151600924,
      "overall_prosody": 1.3797093027428582
    },
    {
      "filename": "akan13.wav",
      "f0_rmse": 1.1434821425249717,
      "f0_correlation": 0.8262794607988184,
      "tempo_similarity": 1.0,
      "rhythm_similarity": 0.9509793394410424,
      "stress_similarity": 0.9747046203504683,
      "overall_prosody": 0.9790891126230601
    },
    {
      "filename": "hausa01.wav",
      "f0_rmse": 5.167374131715612,
      "f0_correlation": 0.5420169297299182,
      "tempo_similarity": 1.0,
      "rhythm_similarity": 0.9239094685988221,
      "stress_similarity": 0.9822742108595885,
      "overall_prosody": 1.7231149481807884
    },
    {
      "filename": "hausa02.wav",
      "f0_rmse": 4.588980828896472,
      "f0_correlation": 0.54768681973547,
      "tempo_similarity": 1.0,
      "rhythm_similarity": 0.9411216127760473,
      "stress_similarity": 0.9782275799799798,
      "overall_prosody": 1.6112033682775937
    },
    {
      "filename": "hausa03.wav",
      "f0_rmse": 3.8460300905808027,
      "f0_correlation": 0.6385165138558274,
      "tempo_similarity": 0.95,
      "rhythm_similarity": 0.9224789486492821,
      "stress_similarity": 0.9828781770982932,
      "overall_prosody": 1.4679807460368413
    },
    {
      "filename": "hausa04.wav",
      "f0_rmse": 5.2964109227499945,
      "f0_correlation": 0.38175380468202874,
      "tempo_similarity": 1.0,
      "rhythm_similarity": 0.9518713772297462,
      "stress_similarity": 0.9593260673170776,
      "overall_prosody": 1.7178724343957694
    },
    {
      "filename": "hausa05.wav",
      "f0_rmse": 2.3138158091221377,
      "f0_correlation": 0.834601205673711,
      "tempo_similarity": 1.0,
      "rhythm_similarity": 0.9222744651537133,
      "stress_similarity": 0.9765714143500762,
      "overall_prosody": 1.2094525788599275
    },
    {
      "filename": "hausa06.wav",
      "f0_rmse": 1.6949749188764411,
      "f0_correlation": 0.8026189893772012,
      "tempo_similarity": 1.0,
      "rhythm_similarity": 0.935713692292323,
      "stress_similarity": 0.9805700592319353,
      "overall_prosody": 1.08277553195558
    },
    {
      "filename": "hausa07.wav",
      "f0_rmse": 6.022695626948066,
      "f0_correlation": 0.40952253108355174,
      "tempo_similarity": 1.0,
      "rhythm_similarity": 0.8798302765753783,
      "stress_similarity": 0.9735706710577244,
      "overall_prosody": 1.8571238211329437
    },
    {
      "filename": "hausa08.wav",
      "f0_rmse": 3.4815431225631728,
      "f0_correlation": 0.552843880995785,
      "tempo_similarity": 1.0,
      "rhythm_similarity": 0.9706696811899931,
      "stress_similarity": 0.9643980704983095,
      "overall_prosody": 1.3938909510494522
    },
    {
      "filename": "hausa09.wav",
      "f0_rmse": 4.014515529566856,
      "f0_correlation": 0.5984165850057785,
      "tempo_similarity": 0.5185185185185186,
      "rhythm_similarity": 0.9785246544693907,
      "stress_similarity": 0.9728469494792643,
      "overall_prosody": 1.416564447407962
    },
    {
      "filename": "hausa10.wav",
      "f0_rmse": 4.173598929144,
      "f0_correlation": 0.6096167451744221,
      "tempo_similarity": 1.0,
      "rhythm_similarity": 0.9350371383328526,
      "stress_similarity": 0.9689416982959487,
      "overall_prosody": 1.5374389021894443
    },
    {
      "filename": "hausa11.wav",
      "f0_rmse": 4.03835053877608,
      "f0_correlation": 0.6202832760105516,
      "tempo_similarity": 1.0,
      "rhythm_similarity": 0.9397812530934004,
      "stress_similarity": 0.9693945805491018,
      "overall_prosody": 1.5135619296858267
    },
    {
      "filename": "hausa12.wav",
      "f0_rmse": 4.066089695727589,
      "f0_correlation": 0.402374861281011,
      "tempo_similarity": 1.0,
      "rhythm_similarity": 0.9259947937004234,
      "stress_similarity": 0.9271154598532074,
      "overall_prosody": 1.4643149621124463
    },
    {
      "filename": "hausa13.wav",
      "f0_rmse": 2.0486912728214004,
      "f0_correlation": 0.8334051517477392,
      "tempo_similarity": 1.0,
      "rhythm_similarity": 0.9137386059969193,
      "stress_similarity": 0.9742547605849796,
      "overall_prosody": 1.1540179582302077
    },
    {
      "filename": "igbo01.wav",
      "f0_rmse": 4.372312624444733,
      "f0_correlation": 0.6359161772699249,
      "tempo_similarity": 0.9166666666666666,
      "rhythm_similarity": 0.9544190322418156,
      "stress_similarity": 0.9692532314846483,
      "overall_prosody": 1.5697135464215577
    },
    {
      "filename": "igbo02.wav",
      "f0_rmse": 5.068757698387657,
      "f0_correlation": 0.7141756983987725,
      "tempo_similarity": 1.0,
      "rhythm_similarity": 0.9524801235123026,
      "stress_similarity": 0.9736486843208471,
      "overall_prosody": 1.741812440923916
    },
    {
      "filename": "igbo03.wav",
      "f0_rmse": 4.291101587633245,
      "f0_correlation": 0.6307120316462,
      "tempo_similarity": 1.0,
      "rhythm_similarity": 0.9726010511768235,
      "stress_similarity": 0.9667852421795873,
      "overall_prosody": 1.5722399825271711
    },
    {
      "filename": "igbo04.wav",
      "f0_rmse": 1.6612985918367007,
      "f0_correlation": 0.8818121749195267,
      "tempo_similarity": 1.0,
      "rhythm_similarity": 0.8358788273693395,
      "stress_similarity": 0.951206791439924,
      "overall_prosody": 1.0660392771130982
    },
    {
      "filename": "igbo05.wav",
      "f0_rmse": 2.3861962549598745,
      "f0_correlation": 0.8523487614867272,
      "tempo_similarity": 1.0,
      "rhythm_similarity": 0.9075152125494068,
      "stress_similarity": 0.9231824475893882,
      "overall_prosody": 1.2138485353170794
    },
    {
      "filename": "igbo06.wav",
      "f0_rmse": 3.170223406413236,
      "f0_correlation": 0.7267094612551191,
      "tempo_similarity": 0.7142857142857144,
      "rhythm_similarity": 0.8765239386036938,
      "stress_similarity": 0.9378228345304087,
      "overall_prosody": 1.2851130710176346
    },
    {
      "filename": "igbo07.wav",
      "f0_rmse": 3.5886854141170907,
      "f0_correlation": 0.6438672003495213,
      "tempo_similarity": 1.0,
      "rhythm_similarity": 0.9824391802734334,
      "stress_similarity": 0.9270589709354804,
      "overall_prosody": 1.4284101531351052
    },
    {
      "filename": "igbo08.wav",
      "f0_rmse": 3.287016149619295,
      "f0_correlation": 0.7606943002477041,
      "tempo_similarity": 1.0,
      "rhythm_similarity": 0.9231434574864742,
      "stress_similarity": 0.9294217990590061,
      "overall_prosody": 1.380055141282496
    },
    {
      "filename": "igbo09.wav",
      "f0_rmse": 3.789120482329725,
      "f0_correlation": 0.6696167115122987,
      "tempo_similarity": 1.0,
      "rhythm_similarity": 0.9700126998109455,
      "stress_similarity": 0.9473788380971662,
      "overall_prosody": 1.4752257463500271
    },
    {
      "filename": "igbo10.wav",
      "f0_rmse": 3.2359225032707326,
      "f0_correlation": 0.6634988015051925,
      "tempo_similarity": 1.0,
      "rhythm_similarity": 0.9311620715830423,
      "stress_similarity": 0.9752823838148449,
      "overall_prosody": 1.3611731520347625
    },
    {
      "filename": "igbo11.wav",
      "f0_rmse": 4.75990566205515,
      "f0_correlation": 0.5487270889982819,
      "tempo_similarity": 1.0,
      "rhythm_similarity": 0.851623863067297,
      "stress_similarity": 0.9573562251857733,
      "overall_prosody": 1.6235225678613006
    },
    {
      "filename": "igbo12.wav",
      "f0_rmse": 4.572478666057333,
      "f0_correlation": 0.5022237524545098,
      "tempo_similarity": 1.0,
      "rhythm_similarity": 0.9737395835822329,
      "stress_similarity": 0.9777193409246152,
      "overall_prosody": 1.6052322686037381
    },
    {
      "filename": "igbo13.wav",
      "f0_rmse": 3.856692465488913,
      "f0_correlation": 0.6190626797385884,
      "tempo_similarity": 0.8823529411764706,
      "rhythm_similarity": 0.9508682056566052,
      "stress_similarity": 0.9352375220651852,
      "overall_prosody": 1.4488427628251526
    },
    {
      "filename": "ijaw01.wav",
      "f0_rmse": 7.823916698173626,
      "f0_correlation": 0.6079038560142492,
      "tempo_similarity": 1.0,
      "rhythm_similarity": 0.992842535885224,
      "stress_similarity": 0.9708663287330752,
      "overall_prosody": 2.2791058837612352
    },
    {
      "filename": "ijaw02.wav",
      "f0_rmse": 7.0653198138451305,
      "f0_correlation": 0.518727430652766,
      "tempo_similarity": 1.0,
      "rhythm_similarity": 0.9718371703695586,
      "stress_similarity": 0.9733773241772499,
      "overall_prosody": 2.105852347808941
    },
    {
      "filename": "ijaw03.wav",
      "f0_rmse": 8.126563384459478,
      "f0_correlation": 0.6165432000845327,
      "tempo_similarity": 0.4736842105263158,
      "rhythm_similarity": 0.9284342020621792,
      "stress_similarity": 0.9289691589744176,
      "overall_prosody": 2.2148388312213845
    },
    {
      "filename": "ijaw04.wav",
      "f0_rmse": 8.165045765646008,
      "f0_correlation": 0.5692019637668777,
      "tempo_similarity": 1.0,
      "rhythm_similarity": 0.9739569168064101,
      "stress_similarity": 0.9755579524939676,
      "overall_prosody": 2.3367525197426526
    },
    {
      "filename": "ijaw05.wav",
      "f0_rmse": 8.258532355174928,
      "f0_correlation": 0.47557659774447564,
      "tempo_similarity": 0.9545454545454546,
      "rhythm_similarity": 0.9570791266303014,
      "stress_similarity": 0.9663166039409176,
      "overall_prosody": 2.3224100276072157
    },
    {
      "filename": "ijaw06.wav",
      "f0_rmse": 7.190023828616935,
      "f0_correlation": 0.407828034813983,
      "tempo_similarity": 1.0,
      "rhythm_similarity": 0.9850977169250497,
      "stress_similarity": 0.9730322098941273,
      "overall_prosody": 2.111196358050019
    },
    {
      "filename": "ijaw07.wav",
      "f0_rmse": 8.147138066314097,
      "f0_correlation": 0.5084740152480814,
      "tempo_similarity": 1.0,
      "rhythm_similarity": 0.9544605813142393,
      "stress_similarity": 0.9745176225463567,
      "overall_prosody": 2.3169180570845547
    },
    {
      "filename": "ijaw08.wav",
      "f0_rmse": 8.69747941659979,
      "f0_correlation": 0.3423842385821948,
      "tempo_similarity": 1.0,
      "rhythm_similarity": 0.8880967044912791,
      "stress_similarity": 0.9531534917742663,
      "overall_prosody": 2.3762227702895062
    },
    {
      "filename": "ijaw09.wav",
      "f0_rmse": 7.4173370161755106,
      "f0_correlation": 0.46236530017966476,
      "tempo_similarity": 0.9166666666666666,
      "rhythm_similarity": 0.9730038441418661,
      "stress_similarity": 0.9710907923687517,
      "overall_prosody": 2.1480927239064918
    },
    {
      "filename": "ijaw10.wav",
      "f0_rmse": 8.741255926780658,
      "f0_correlation": 0.4549050033339726,
      "tempo_similarity": 1.0,
      "rhythm_similarity": 0.9812439748043631,
      "stress_similarity": 0.9706577452355706,
      "overall_prosody": 2.429612530030913
    },
    {
      "filename": "ijaw11.wav",
      "f0_rmse": 7.924286922784952,
      "f0_correlation": 0.3193422916744859,
      "tempo_similarity": 1.0,
      "rhythm_similarity": 0.9787236900144907,
      "stress_similarity": 0.9700033365695964,
      "overall_prosody": 2.238471248208705
    },
    {
      "filename": "ijaw12.wav",
      "f0_rmse": 7.159771520411236,
      "f0_correlation": 0.5420239498147706,
      "tempo_similarity": 1.0,
      "rhythm_similarity": 0.9405614195726202,
      "stress_similarity": 0.9705744434999632,
      "overall_prosody": 2.122586266659718
    },
    {
      "filename": "ijaw13.wav",
      "f0_rmse": 7.968457468078211,
      "f0_correlation": 0.48305868155021214,
      "tempo_similarity": 1.0,
      "rhythm_similarity": 0.8062218176800262,
      "stress_similarity": 0.9466408097462875,
      "overall_prosody": 2.2408757554109475
    },
    {
      "filename": "shona01.wav",
      "f0_rmse": 3.9487616449342147,
      "f0_correlation": 0.6276506843338157,
      "tempo_similarity": 0.6666666666666667,
      "rhythm_similarity": 0.9721803014966475,
      "stress_similarity": 0.9756766641953641,
      "overall_prosody": 1.438187192325342
    },
    {
      "filename": "shona02.wav",
      "f0_rmse": 3.8797225411942162,
      "f0_correlation": 0.6285777306141198,
      "tempo_similarity": 1.0,
      "rhythm_similarity": 0.952757866836951,
      "stress_similarity": 0.9538306723298952,
      "overall_prosody": 1.4829777621950364
    },
    {
      "filename": "shona03.wav",
      "f0_rmse": 3.7928206868208605,
      "f0_correlation": 0.7034722353756154,
      "tempo_similarity": 0.9411764705882353,
      "rhythm_similarity": 0.9936513582361943,
      "stress_similarity": 0.9710107436098456,
      "overall_prosody": 1.4804262989261503
    },
    {
      "filename": "shona04.wav",
      "f0_rmse": 3.6002645270606184,
      "f0_correlation": 0.6727888145859192,
      "tempo_similarity": 1.0,
      "rhythm_similarity": 0.9832377558997645,
      "stress_similarity": 0.9590070271342017,
      "overall_prosody": 1.443059624936101
    },
    {
      "filename": "shona05.wav",
      "f0_rmse": 4.068231553741401,
      "f0_correlation": 0.6198928728274724,
      "tempo_similarity": 1.0,
      "rhythm_similarity": 0.9499661786456295,
      "stress_similarity": 0.9625927330330257,
      "overall_prosody": 1.5201366676495058
    },
    {
      "filename": "shona06.wav",
      "f0_rmse": 4.851041260853715,
      "f0_correlation": 0.4397597070649002,
      "tempo_similarity": 1.0,
      "rhythm_similarity": 0.9641888993954113,
      "stress_similarity": 0.9703603079936337,
      "overall_prosody": 1.6450700350615322
    },
    {
      "filename": "shona07.wav",
      "f0_rmse": 4.471478812773867,
      "f0_correlation": 0.5593179639951428,
      "tempo_similarity": 1.0,
      "rhythm_similarity": 0.9131480052533283,
      "stress_similarity": 0.9628664168330894,
      "overall_prosody": 1.5813622397710856
    },
    {
      "filename": "shona08.wav",
      "f0_rmse": 4.229091375436148,
      "f0_correlation": 0.5875621095724225,
      "tempo_similarity": 1.0,
      "rhythm_similarity": 0.9359623812609037,
      "stress_similarity": 0.9560940790801475,
      "overall_prosody": 1.5417419890699242
    },
    {
      "filename": "shona09.wav",
      "f0_rmse": 3.9327188471227137,
      "f0_correlation": 0.648136629104467,
      "tempo_similarity": 0.8333333333333334,
      "rhythm_similarity": 0.9781735941795678,
      "stress_similarity": 0.9803879637893758,
      "overall_prosody": 1.4745500735058914
    },
    {
      "filename": "shona10.wav",
      "f0_rmse": 4.203260791393715,
      "f0_correlation": 0.6076564189724571,
      "tempo_similarity": 1.0,
      "rhythm_similarity": 0.971291095368513,
      "stress_similarity": 0.9657669894228289,
      "overall_prosody": 1.5495950590315029
    },
    {
      "filename": "shona11.wav",
      "f0_rmse": 3.7021727180337654,
      "f0_correlation": 0.6313804553962332,
      "tempo_similarity": 1.0,
      "rhythm_similarity": 0.9545830295935188,
      "stress_similarity": 0.9615879248658126,
      "overall_prosody": 1.449944825577866
    },
    {
      "filename": "shona12.wav",
      "f0_rmse": 3.6366846252793565,
      "f0_correlation": 0.5920083942480517,
      "tempo_similarity": 0.6470588235294117,
      "rhythm_similarity": 0.9072936373147913,
      "stress_similarity": 0.9615721756918754,
      "overall_prosody": 1.3489235312126975
    },
    {
      "filename": "shona13.wav",
      "f0_rmse": 3.3554168398570394,
      "f0_correlation": 0.6932213809173312,
      "tempo_similarity": 1.0,
      "rhythm_similarity": 0.9912840766926555,
      "stress_similarity": 0.9629395269416909,
      "overall_prosody": 1.4005723648817434
    },
    {
      "filename": "swahili,_kamba01.wav",
      "f0_rmse": 7.401958750250607,
      "f0_correlation": 0.3680019643749704,
      "tempo_similarity": 1.0,
      "rhythm_similarity": 0.938254545999065,
      "stress_similarity": 0.8160233612660468,
      "overall_prosody": 2.104847724378138
    },
    {
      "filename": "swahili,_kamba02.wav",
      "f0_rmse": 7.498216617286111,
      "f0_correlation": 0.3998291598274435,
      "tempo_similarity": 1.0,
      "rhythm_similarity": 0.9376902926900528,
      "stress_similarity": 0.9581756472016446,
      "overall_prosody": 2.1587823434010507
    },
    {
      "filename": "swahili,_kamba03.wav",
      "f0_rmse": 8.646696754478766,
      "f0_correlation": 0.4595849930259399,
      "tempo_similarity": 0.9285714285714285,
      "rhythm_similarity": 0.9526899368633679,
      "stress_similarity": 0.9163450524010324,
      "overall_prosody": 2.3807776330681074
    },
    {
      "filename": "swahili,_kamba04.wav",
      "f0_rmse": 6.242810242946819,
      "f0_correlation": 0.4790802452104109,
      "tempo_similarity": 1.0,
      "rhythm_similarity": 0.9906406422520762,
      "stress_similarity": 0.7535084302917716,
      "overall_prosody": 1.8932079121402154
    },
    {
      "filename": "swahili,_kamba05.wav",
      "f0_rmse": 7.928965971626437,
      "f0_correlation": 0.03174496702709086,
      "tempo_similarity": 1.0,
      "rhythm_similarity": 0.9859809589009095,
      "stress_similarity": 0.93657941215079,
      "overall_prosody": 2.1766542619410454
    },
    {
      "filename": "swahili,_kamba06.wav",
      "f0_rmse": 8.245295340671074,
      "f0_correlation": 0.3041866739576941,
      "tempo_similarity": 0.5555555555555556,
      "rhythm_similarity": 0.9247152601118563,
      "stress_similarity": 0.7991856864290496,
      "overall_prosody": 2.165787703345046
    },
    {
      "filename": "swahili,_kamba07.wav",
      "f0_rmse": 5.8915434065481165,
      "f0_correlation": 0.6946518295959624,
      "tempo_similarity": 0.6190476190476191,
      "rhythm_similarity": 0.9414042962852771,
      "stress_similarity": 0.9365633508858933,
      "overall_prosody": 1.8166421004725735
    },
    {
      "filename": "swahili,_kamba08.wav",
      "f0_rmse": 4.5224644415900945,
      "f0_correlation": 0.6041931157680663,
      "tempo_similarity": 0.6666666666666667,
      "rhythm_similarity": 0.9715874140774217,
      "stress_similarity": 0.82623518382298,
      "overall_prosody": 1.518229364385046
    },
    {
      "filename": "swahili,_kamba09.wav",
      "f0_rmse": 6.582868377382709,
      "f0_correlation": 0.6255899071553345,
      "tempo_similarity": 1.0,
      "rhythm_similarity": 1.0,
      "stress_similarity": 0.9012432679241906,
      "overall_prosody": 2.0219403104924467
    },
    {
      "filename": "swahili,_kamba10.wav",
      "f0_rmse": 5.896074591257114,
      "f0_correlation": 0.032059342995628314,
      "tempo_similarity": 1.0,
      "rhythm_similarity": 0.9225129521895394,
      "stress_similarity": 0.7977071043991948,
      "overall_prosody": 1.7296707981682953
    },
    {
      "filename": "swahili,_kamba11.wav",
      "f0_rmse": 6.054224108172951,
      "f0_correlation": 0.4491893573966844,
      "tempo_similarity": 1.0,
      "rhythm_similarity": 0.9885576397540583,
      "stress_similarity": 0.9255355606749013,
      "overall_prosody": 1.8835013331997192
    },
    {
      "filename": "swahili,_kamba12.wav",
      "f0_rmse": 4.498602057158171,
      "f0_correlation": 0.25940766867594145,
      "tempo_similarity": 1.0,
      "rhythm_similarity": 0.9934896741500154,
      "stress_similarity": 0.8149979384471753,
      "overall_prosody": 1.5132994676862606
    },
    {
      "filename": "swahili,_kikuyu01.wav",
      "f0_rmse": 4.296431988817698,
      "f0_correlation": 0.5641050757493957,
      "tempo_similarity": 0.6923076923076923,
      "rhythm_similarity": 0.8723919961443494,
      "stress_similarity": 0.9844369312019157,
      "overall_prosody": 1.4819347368442102
    },
    {
      "filename": "swahili,_kikuyu02.wav",
      "f0_rmse": 5.105847697431177,
      "f0_correlation": 0.5320325527636589,
      "tempo_similarity": 1.0,
      "rhythm_similarity": 0.9568438154525798,
      "stress_similarity": 0.9545845589083403,
      "overall_prosody": 1.7098617249111512
    },
    {
      "filename": "swahili,_kikuyu03.wav",
      "f0_rmse": 5.409058388106014,
      "f0_correlation": 0.5615887216088644,
      "tempo_similarity": 1.0,
      "rhythm_similarity": 0.9201804281957835,
      "stress_similarity": 0.9451422789521804,
      "overall_prosody": 1.7671939633725686
    },
    {
      "filename": "swahili,_kikuyu04.wav",
      "f0_rmse": 3.537718183487876,
      "f0_correlation": 0.37561800096763176,
      "tempo_similarity": 1.0,
      "rhythm_similarity": 0.9972051206449313,
      "stress_similarity": 0.9768648231674049,
      "overall_prosody": 1.377481225653569
    },
    {
      "filename": "swahili,_kikuyu05.wav",
      "f0_rmse": 5.245377255228107,
      "f0_correlation": 0.40813641527804884,
      "tempo_similarity": 1.0,
      "rhythm_similarity": 0.9946277788600512,
      "stress_similarity": 0.9627012923590713,
      "overall_prosody": 1.7221685483450557
    },
    {
      "filename": "swahili,_kikuyu06.wav",
      "f0_rmse": 2.9055884148962385,
      "f0_correlation": 0.5885218077416059,
      "tempo_similarity": 1.0,
      "rhythm_similarity": 0.9430126452025168,
      "stress_similarity": 0.9758963103104297,
      "overall_prosody": 1.2826038356301581
    },
    {
      "filename": "swahili,_kikuyu07.wav",
      "f0_rmse": 4.996394942909873,
      "f0_correlation": 0.6881339158134697,
      "tempo_similarity": 0.9411764705882353,
      "rhythm_similarity": 0.9661303162301847,
      "stress_similarity": 0.9706861827473283,
      "overall_prosody": 1.7125043656578185
    },
    {
      "filename": "swahili,_kikuyu08.wav",
      "f0_rmse": 4.554490915605511,
      "f0_correlation": 0.43364547344248977,
      "tempo_similarity": 1.0,
      "rhythm_similarity": 0.9918781372776914,
      "stress_similarity": 0.9730809430577045,
      "overall_prosody": 1.5906190938766793
    },
    {
      "filename": "swahili,_kikuyu09.wav",
      "f0_rmse": 3.941454948861573,
      "f0_correlation": 0.5072399019692816,
      "tempo_similarity": 1.0,
      "rhythm_similarity": 0.9413050614637228,
      "stress_similarity": 0.9732980609552273,
      "overall_prosody": 1.472659594649961
    },
    {
      "filename": "swahili,_kikuyu10.wav",
      "f0_rmse": 5.862212277187159,
      "f0_correlation": 0.517336696103528,
      "tempo_similarity": 0.923076923076923,
      "rhythm_similarity": 0.9388864023104823,
      "stress_similarity": 0.9713606232238994,
      "overall_prosody": 1.8425745843803985
    },
    {
      "filename": "swahili,_kikuyu11.wav",
      "f0_rmse": 2.5431958580265714,
      "f0_correlation": 0.782961744903073,
      "tempo_similarity": 1.0,
      "rhythm_similarity": 0.9383996070523593,
      "stress_similarity": 0.9664606795130033,
      "overall_prosody": 1.2462035778990015
    },
    {
      "filename": "swahili,_kikuyu12.wav",
      "f0_rmse": 5.765855736974234,
      "f0_correlation": 0.45666151546201994,
      "tempo_similarity": 1.0,
      "rhythm_similarity": 0.9785818798150405,
      "stress_similarity": 0.9727639988290888,
      "overall_prosody": 1.8347726262160766
    },
    {
      "filename": "swahili01.wav",
      "f0_rmse": 7.215713023248209,
      "f0_correlation": 0.342042596177557,
      "tempo_similarity": 1.0,
      "rhythm_similarity": 0.9614730503259837,
      "stress_similarity": 0.9068254419914432,
      "overall_prosody": 2.0852108223486385
    },
    {
      "filename": "swahili02.wav",
      "f0_rmse": 2.7260982250804258,
      "f0_correlation": 0.6165847547887647,
      "tempo_similarity": 1.0,
      "rhythm_similarity": 0.9443705016148682,
      "stress_similarity": 0.9512923443368402,
      "overall_prosody": 1.2476691651641798
    },
    {
      "filename": "swahili03.wav",
      "f0_rmse": 2.8928609962496106,
      "f0_correlation": 0.732853006992147,
      "tempo_similarity": 1.0,
      "rhythm_similarity": 0.9967276161891463,
      "stress_similarity": 0.9743418595167936,
      "overall_prosody": 1.3193566957895393
    },
    {
      "filename": "swahili04.wav",
      "f0_rmse": 4.986770625210207,
      "f0_correlation": 0.4939078250103178,
      "tempo_similarity": 1.0,
      "rhythm_similarity": 0.9673240787604662,
      "stress_similarity": 0.9428745452109362,
      "overall_prosody": 1.6781754148383854
    },
    {
      "filename": "swahili05.wav",
      "f0_rmse": 4.473165248706554,
      "f0_correlation": 0.6689759197602806,
      "tempo_similarity": 1.0,
      "rhythm_similarity": 0.9317622196895601,
      "stress_similarity": 0.9810829114445734,
      "overall_prosody": 1.6109972599201936
    },
    {
      "filename": "swahili06.wav",
      "f0_rmse": 0.961272252649834,
      "f0_correlation": 0.7454760100962766,
      "tempo_similarity": 0.76,
      "rhythm_similarity": 0.9651464968167186,
      "stress_similarity": 0.9383164336437863,
      "overall_prosody": 0.8740422386413231
    },
    {
      "filename": "swahili07.wav",
      "f0_rmse": 2.1865504889268133,
      "f0_correlation": 0.5364521239549324,
      "tempo_similarity": 0.7272727272727273,
      "rhythm_similarity": 0.8315708136885153,
      "stress_similarity": 0.8901303416104875,
      "overall_prosody": 1.034395299090695
    },
    {
      "filename": "swahili08.wav",
      "f0_rmse": 2.2899658005943992,
      "f0_correlation": 0.6377843738909688,
      "tempo_similarity": 0.5555555555555556,
      "rhythm_similarity": 0.8925102730274014,
      "stress_similarity": 0.9459328218436219,
      "overall_prosody": 1.0643497649823892
    },
    {
      "filename": "swahili09.wav",
      "f0_rmse": 7.601408723763589,
      "f0_correlation": 0.23253212963726053,
      "tempo_similarity": 1.0,
      "rhythm_similarity": 0.9826478910371117,
      "stress_similarity": 0.8707420039911071,
      "overall_prosody": 2.137466149685814
    },
    {
      "filename": "swahili10.wav",
      "f0_rmse": 7.064452810038494,
      "f0_correlation": 0.4120257123366314,
      "tempo_similarity": 0.625,
      "rhythm_similarity": 0.9227015648361541,
      "stress_similarity": 0.9460848054345308,
      "overall_prosody": 1.994052978529162
    },
    {
      "filename": "swahili11.wav",
      "f0_rmse": 5.7937347969886375,
      "f0_correlation": 0.4008577666520065,
      "tempo_similarity": 1.0,
      "rhythm_similarity": 0.9077169499847015,
      "stress_similarity": 0.9542873900623395,
      "overall_prosody": 1.8113193807375367
    },
    {
      "filename": "swahili12.wav",
      "f0_rmse": 2.5035936228854965,
      "f0_correlation": 0.7885092589966683,
      "tempo_similarity": 0.52,
      "rhythm_similarity": 0.8313896974104327,
      "stress_similarity": 0.9647007588421674,
      "overall_prosody": 1.1216386676269532
    },
    {
      "filename": "swahili13.wav",
      "f0_rmse": 2.751518179774294,
      "f0_correlation": 0.5106615458841445,
      "tempo_similarity": 1.0,
      "rhythm_similarity": 0.9426764892574071,
      "stress_similarity": 0.9545160089582994,
      "overall_prosody": 1.2318744447748287
    },
    {
      "filename": "tswana01.wav",
      "f0_rmse": 3.127919687276188,
      "f0_correlation": 0.5321309129196746,
      "tempo_similarity": 1.0,
      "rhythm_similarity": 0.9794603678768394,
      "stress_similarity": 0.7961658771417335,
      "overall_prosody": 1.2871353690428873
    },
    {
      "filename": "tswana02.wav",
      "f0_rmse": 2.576833360311217,
      "f0_correlation": 0.3761162457897641,
      "tempo_similarity": 0.6875,
      "rhythm_similarity": 0.9057917440999093,
      "stress_similarity": 0.9432320691533109,
      "overall_prosody": 1.0978946838708403
    },
    {
      "filename": "tswana03.wav",
      "f0_rmse": 3.2240768807850047,
      "f0_correlation": 0.4940183087320443,
      "tempo_similarity": 1.0,
      "rhythm_similarity": 0.9732578656628548,
      "stress_similarity": 0.6967278393319378,
      "overall_prosody": 1.2776161789023681
    },
    {
      "filename": "tswana04.wav",
      "f0_rmse": 0.4980033784829347,
      "f0_correlation": 0.9577953018988103,
      "tempo_similarity": 1.0,
      "rhythm_similarity": 0.8842366396839199,
      "stress_similarity": 0.8799371777228533,
      "overall_prosody": 0.8439944995577037
    },
    {
      "filename": "tswana05.wav",
      "f0_rmse": 2.3757393653355017,
      "f0_correlation": 0.49035643940735485,
      "tempo_similarity": 1.0,
      "rhythm_similarity": 0.9509894947129305,
      "stress_similarity": 0.5058967692416388,
      "overall_prosody": 1.0645964137394852
    },
    {
      "filename": "tswana06.wav",
      "f0_rmse": 1.365425805865385,
      "f0_correlation": 0.667289206794577,
      "tempo_similarity": 1.0,
      "rhythm_similarity": 0.7568735753865525,
      "stress_similarity": 0.9663892087611488,
      "overall_prosody": 0.9511955593615327
    },
    {
      "filename": "tswana07.wav",
      "f0_rmse": 2.0945333722789004,
      "f0_correlation": 0.21228619622781333,
      "tempo_similarity": 0.923076923076923,
      "rhythm_similarity": 0.7442600466856556,
      "stress_similarity": 0.9191614343807382,
      "overall_prosody": 0.9786635945300061
    },
    {
      "filename": "tswana08.wav",
      "f0_rmse": 2.2936194138577153,
      "f0_correlation": 0.39391680824137965,
      "tempo_similarity": 1.0,
      "rhythm_similarity": 0.6120047095405936,
      "stress_similarity": 0.856448997442144,
      "overall_prosody": 1.0311979858163665
    },
    {
      "filename": "tswana09.wav",
      "f0_rmse": 1.8259422733300275,
      "f0_correlation": 0.3311281927942283,
      "tempo_similarity": 1.0,
      "rhythm_similarity": 1.0,
      "stress_similarity": 0.9540829934861611,
      "overall_prosody": 1.0222306919220834
    },
    {
      "filename": "tswana10.wav",
      "f0_rmse": 2.2591191607689542,
      "f0_correlation": 0.5176105395444284,
      "tempo_similarity": 1.0,
      "rhythm_similarity": 1.0,
      "stress_similarity": 0.840474672025848,
      "overall_prosody": 1.1234408744678461
    },
    {
      "filename": "tswana11.wav",
      "f0_rmse": 3.0534205001262347,
      "f0_correlation": 0.32792356333370554,
      "tempo_similarity": 0.6923076923076923,
      "rhythm_similarity": 0.8960155647659807,
      "stress_similarity": 0.5020659135634059,
      "overall_prosody": 1.0943466468194039
    },
    {
      "filename": "tswana12.wav",
      "f0_rmse": 3.4931607975138412,
      "f0_correlation": 0.3134535035346327,
      "tempo_similarity": 0.7272727272727273,
      "rhythm_similarity": 0.9035521503007431,
      "stress_similarity": 0.965757529063262,
      "overall_prosody": 1.2806393415370412
    },
    {
      "filename": "unknown01.wav",
      "f0_rmse": 4.914414010226078,
      "f0_correlation": 0.583611775838859,
      "tempo_similarity": 1.0,
      "rhythm_similarity": 0.9724000782405486,
      "stress_similarity": 0.9319491608836967,
      "overall_prosody": 1.6804750050378363
    },
    {
      "filename": "unknown02.wav",
      "f0_rmse": 5.185022072972815,
      "f0_correlation": 0.5487862588757126,
      "tempo_similarity": 0.6666666666666667,
      "rhythm_similarity": 0.9718867990579186,
      "stress_similarity": 0.9678568800753279,
      "overall_prosody": 1.6680437355296884
    },
    {
      "filename": "unknown03.wav",
      "f0_rmse": 5.936057450930544,
      "f0_correlation": 0.5496284564723486,
      "tempo_similarity": 1.0,
      "rhythm_similarity": 0.9818526384669852,
      "stress_similarity": 0.9436176547182507,
      "overall_prosody": 1.8822312401176258
    },
    {
      "filename": "unknown04.wav",
      "f0_rmse": 6.103371988341712,
      "f0_correlation": 0.5751663874915801,
      "tempo_similarity": 0.76,
      "rhythm_similarity": 0.9612042003384905,
      "stress_similarity": 0.9440207124456064,
      "overall_prosody": 1.8687526577234777
    },
    {
      "filename": "unknown05.wav",
      "f0_rmse": 6.401362204471674,
      "f0_correlation": 0.3963164845542019,
      "tempo_similarity": 1.0,
      "rhythm_similarity": 0.7933850254370703,
      "stress_similarity": 0.9374257156332463,
      "overall_prosody": 1.9056978860192384
    },
    {
      "filename": "unknown06.wav",
      "f0_rmse": 6.75767504352165,
      "f0_correlation": 0.4885156642557927,
      "tempo_similarity": 1.0,
      "rhythm_similarity": 0.9828053377039812,
      "stress_similarity": 0.9686971483189701,
      "overall_prosody": 2.039538638760079
    },
    {
      "filename": "unknown07.wav",
      "f0_rmse": 5.69524688176849,
      "f0_correlation": 0.5768358524627127,
      "tempo_similarity": 1.0,
      "rhythm_similarity": 0.9174114081847254,
      "stress_similarity": 0.9363285325762019,
      "overall_prosody": 1.8251645349984258
    },
    {
      "filename": "unknown08.wav",
      "f0_rmse": 6.197685156637186,
      "f0_correlation": 0.54933629295996,
      "tempo_similarity": 1.0,
      "rhythm_similarity": 0.9670010458273182,
      "stress_similarity": 0.925974698454394,
      "overall_prosody": 1.9279994387757717
    },
    {
      "filename": "unknown09.wav",
      "f0_rmse": 5.413377179333738,
      "f0_correlation": 0.5993613942217012,
      "tempo_similarity": 1.0,
      "rhythm_similarity": 0.9486571483206354,
      "stress_similarity": 0.922133718045431,
      "overall_prosody": 1.7767058879843014
    },
    {
      "filename": "unknown10.wav",
      "f0_rmse": 5.4415888437380335,
      "f0_correlation": 0.6341053097014083,
      "tempo_similarity": 1.0,
      "rhythm_similarity": 0.9084398912371989,
      "stress_similarity": 0.9551018738173813,
      "overall_prosody": 1.7878471836988044
    },
    {
      "filename": "unknown11.wav",
      "f0_rmse": 4.342906256039344,
      "f0_correlation": 0.589754479717344,
      "tempo_similarity": 0.8571428571428572,
      "rhythm_similarity": 0.9490470046160748,
      "stress_similarity": 0.9609816184532995,
      "overall_prosody": 1.539966443193784
    },
    {
      "filename": "unknown12.wav",
      "f0_rmse": 6.297353614459514,
      "f0_correlation": 0.5524577865017911,
      "tempo_similarity": 0.6875,
      "rhythm_similarity": 0.9716453809990493,
      "stress_similarity": 0.95140282296395,
      "overall_prosody": 1.8920719209848607
    },
    {
      "filename": "yoruba01.wav",
      "f0_rmse": 6.839685726869135,
      "f0_correlation": 0.5062597726504378,
      "tempo_similarity": 1.0,
      "rhythm_similarity": 0.9703408645143557,
      "stress_similarity": 0.9676736172777783,
      "overall_prosody": 2.0567919962623415
    },
    {
      "filename": "yoruba02.wav",
      "f0_rmse": 6.325317305878693,
      "f0_correlation": 0.5608788597003531,
      "tempo_similarity": 0.9375,
      "rhythm_similarity": 0.9618607219548261,
      "stress_similarity": 0.9660059320127858,
      "overall_prosody": 1.9503125639093315
    },
    {
      "filename": "yoruba03.wav",
      "f0_rmse": 6.042172856715663,
      "f0_correlation": 0.5040277889771854,
      "tempo_similarity": 1.0,
      "rhythm_similarity": 0.9340048606159872,
      "stress_similarity": 0.9761469215115095,
      "overall_prosody": 1.8912704855640687
    },
    {
      "filename": "yoruba04.wav",
      "f0_rmse": 6.173909432459947,
      "f0_correlation": 0.6719753104841012,
      "tempo_similarity": 1.0,
      "rhythm_similarity": 0.9029495364003675,
      "stress_similarity": 0.9687232560427148,
      "overall_prosody": 1.9435115070774263
    },
    {
      "filename": "yoruba05.wav",
      "f0_rmse": 5.363660829666236,
      "f0_correlation": 0.5384197834380053,
      "tempo_similarity": 0.9444444444444444,
      "rhythm_similarity": 0.9190179683052517,
      "stress_similarity": 0.9765549158996902,
      "overall_prosody": 1.7484195883507254
    },
    {
      "filename": "yoruba06.wav",
      "f0_rmse": 6.533116076704807,
      "f0_correlation": 0.5565542277507477,
      "tempo_similarity": 1.0,
      "rhythm_similarity": 0.9685752501795957,
      "stress_similarity": 0.9627960986967057,
      "overall_prosody": 2.004208330666371
    },
    {
      "filename": "yoruba07.wav",
      "f0_rmse": 8.924243925210451,
      "f0_correlation": 0.5307041354930907,
      "tempo_similarity": 1.0,
      "rhythm_similarity": 0.9510843715894723,
      "stress_similarity": 0.9718717220621998,
      "overall_prosody": 2.475580830871043
    },
    {
      "filename": "yoruba08.wav",
      "f0_rmse": 5.163339769665387,
      "f0_correlation": 0.4984474634150265,
      "tempo_similarity": 1.0,
      "rhythm_similarity": 0.9948171308103911,
      "stress_similarity": 0.9694707026174616,
      "overall_prosody": 1.7252150133016535
    },
    {
      "filename": "yoruba09.wav",
      "f0_rmse": 6.621494586445446,
      "f0_correlation": 0.518170273347469,
      "tempo_similarity": 0.7777777777777779,
      "rhythm_similarity": 0.8331619533109234,
      "stress_similarity": 0.9705063783182173,
      "overall_prosody": 1.9442221938399669
    },
    {
      "filename": "yoruba10.wav",
      "f0_rmse": 1.7774411879611374,
      "f0_correlation": 0.6271523677906612,
      "tempo_similarity": 0.9444444444444444,
      "rhythm_similarity": 0.893867887011236,
      "stress_similarity": 0.8126793626964985,
      "overall_prosody": 1.0111170499807955
    },
    {
      "filename": "yoruba11.wav",
      "f0_rmse": 1.7305560199137378,
      "f0_correlation": 0.7846735294542113,
      "tempo_similarity": 1.0,
      "rhythm_similarity": 0.9543085711135093,
      "stress_similarity": 0.9235248709153694,
      "overall_prosody": 1.0786125982793657
    },
    {
      "filename": "yoruba12.wav",
      "f0_rmse": 7.739898588692804,
      "f0_correlation": 0.4544331615424423,
      "tempo_similarity": 1.0,
      "rhythm_similarity": 0.9088341310964294,
      "stress_similarity": 0.9698213885581995,
      "overall_prosody": 2.2145974539779756
    },
    {
      "filename": "zulu01.wav",
      "f0_rmse": 4.879451608747248,
      "f0_correlation": 0.1316469722817791,
      "tempo_similarity": 1.0,
      "rhythm_similarity": 1.0,
      "stress_similarity": 0.9888960982779036,
      "overall_prosody": 1.5999989358613862
    },
    {
      "filename": "zulu02.wav",
      "f0_rmse": 5.097419944258604,
      "f0_correlation": 0.5100273221953668,
      "tempo_similarity": 0.9655172413793105,
      "rhythm_similarity": 0.8584045927586212,
      "stress_similarity": 0.7983666368593036,
      "overall_prosody": 1.6459471474902412
    },
    {
      "filename": "zulu03.wav",
      "f0_rmse": 2.8585428000070574,
      "f0_correlation": 0.839592482498233,
      "tempo_similarity": 0.9473684210526316,
      "rhythm_similarity": 0.9002589325033645,
      "stress_similarity": 0.9769343926483393,
      "overall_prosody": 1.304539405741925
    },
    {
      "filename": "zulu04.wav",
      "f0_rmse": 7.946955108080258,
      "f0_correlation": 0.24253826970278577,
      "tempo_similarity": 1.0,
      "rhythm_similarity": 0.8535398954094648,
      "stress_similarity": 0.943969693769942,
      "overall_prosody": 2.19740059339249
    },
    {
      "filename": "zulu05.wav",
      "f0_rmse": 5.34047720831253,
      "f0_correlation": 0.7432779312323221,
      "tempo_similarity": 0.9642857142857142,
      "rhythm_similarity": 0.9517362839214007,
      "stress_similarity": 0.948060524973733,
      "overall_prosody": 1.78956753254514
    },
    {
      "filename": "zulu06.wav",
      "f0_rmse": 0.7271168133037595,
      "f0_correlation": 0.9941079367972313,
      "tempo_similarity": 1.0,
      "rhythm_similarity": 0.8307189138830737,
      "stress_similarity": 0.9928442964125886,
      "overall_prosody": 0.9089575920793307
    },
    {
      "filename": "zulu07.wav",
      "f0_rmse": 2.497775556548016,
      "f0_correlation": 0.5064146063001996,
      "tempo_similarity": 1.0,
      "rhythm_similarity": 0.9227211696057334,
      "stress_similarity": 0.8784022604789916,
      "overall_prosody": 1.1610627185865883
    },
    {
      "filename": "zulu08.wav",
      "f0_rmse": 5.99006138262406,
      "f0_correlation": 0.59749184437925,
      "tempo_similarity": 1.0,
      "rhythm_similarity": 0.9014735669224834,
      "stress_similarity": 0.9637275127652586,
      "overall_prosody": 1.8905508613382103
    },
    {
      "filename": "zulu09.wav",
      "f0_rmse": 7.279816054247755,
      "f0_correlation": 0.2159995419759863,
      "tempo_similarity": 1.0,
      "rhythm_similarity": 0.882137365046286,
      "stress_similarity": 0.9383951183696913,
      "overall_prosody": 2.063269615927944
    },
    {
      "filename": "zulu10.wav",
      "f0_rmse": 2.8946464487371952,
      "f0_correlation": 0.6829112331739999,
      "tempo_similarity": 1.0,
      "rhythm_similarity": 0.8662880028812585,
      "stress_similarity": 0.9394353245856384,
      "overall_prosody": 1.2766562018756182
    },
    {
      "filename": "zulu11.wav",
      "f0_rmse": 7.30574103147346,
      "f0_correlation": 0.5342339415989219,
      "tempo_similarity": 0.9333333333333335,
      "rhythm_similarity": 0.9194292199345732,
      "stress_similarity": 0.9757567554511658,
      "overall_prosody": 2.133698856358291
    },
    {
      "filename": "zulu12.wav",
      "f0_rmse": 5.499227837652187,
      "f0_correlation": 0.4861815670814279,
      "tempo_similarity": 1.0,
      "rhythm_similarity": 0.9153447478972506,
      "stress_similarity": 0.951928286241457,
      "overall_prosody": 1.7705364877744647
    }
  ]
}