{
  "metric": "utmos",
  "audio_dir": "/orange/ufdatastudios/c.okocha/CodecEval-Africa/outputs/afrispeech_multilingual/SemantiCodec_outputs/0.31kbps",
  "num_files": 100,
  "num_scored_files": 100,
  "utmos": 1.4825468564033508,
  "utmos_std": 0.263327237613154,
  "utmos_min": 1.2335519790649414,
  "utmos_max": 3.1008124351501465,
  "per_file": [
    {
      "filename": "common_voice_ig_30477016.wav",
      "utmos": 1.8807321786880493
    },
    {
      "filename": "common_voice_ig_30477017.wav",
      "utmos": 1.5550236701965332
    },
    {
      "filename": "common_voice_ig_30477018.wav",
      "utmos": 1.553251028060913
    },
    {
      "filename": "common_voice_ig_30477019.wav",
      "utmos": 1.5606721639633179
    },
    {
      "filename": "common_voice_ig_30477020.wav",
      "utmos": 1.6133710145950317
    },
    {
      "filename": "common_voice_ig_30689626.wav",
      "utmos": 1.7512729167938232
    },
    {
      "filename": "common_voice_ig_30689627.wav",
      "utmos": 1.65793776512146
    },
    {
      "filename": "common_voice_ig_30689628.wav",
      "utmos": 1.614632248878479
    },
    {
      "filename": "common_voice_ig_30689629.wav",
      "utmos": 1.6986604928970337
    },
    {
      "filename": "common_voice_ig_30689630.wav",
      "utmos": 1.5911023616790771
    },
    {
      "filename": "common_voice_ig_30689631.wav",
      "utmos": 1.409039855003357
    },
    {
      "filename": "common_voice_ig_30689632.wav",
      "utmos": 1.4668855667114258
    },
    {
      "filename": "common_voice_ig_30689633.wav",
      "utmos": 1.4256229400634766
    },
    {
      "filename": "common_voice_ig_30689634.wav",
      "utmos": 1.454100251197815
    },
    {
      "filename": "common_voice_ig_30689635.wav",
      "utmos": 1.7014235258102417
    },
    {
      "filename": "common_voice_ig_30689652.wav",
      "utmos": 1.3179996013641357
    },
    {
      "filename": "common_voice_ig_30689655.wav",
      "utmos": 1.2803239822387695
    },
    {
      "filename": "common_voice_ig_30689656.wav",
      "utmos": 1.2464308738708496
    },
    {
      "filename": "common_voice_ig_30689657.wav",
      "utmos": 1.2646653652191162
    },
    {
      "filename": "common_voice_ig_30689658.wav",
      "utmos": 1.3477579355239868
    },
    {
      "filename": "common_voice_ig_30689665.wav",
      "utmos": 1.5037920475006104
    },
    {
      "filename": "common_voice_ig_30689666.wav",
      "utmos": 1.4332994222640991
    },
    {
      "filename": "common_voice_ig_30689667.wav",
      "utmos": 1.9703534841537476
    },
    {
      "filename": "common_voice_ig_30689668.wav",
      "utmos": 1.4600361585617065
    },
    {
      "filename": "common_voice_ig_30689669.wav",
      "utmos": 1.911896824836731
    },
    {
      "filename": "common_voice_ig_30689997.wav",
      "utmos": 1.6412434577941895
    },
    {
      "filename": "common_voice_ig_30689998.wav",
      "utmos": 1.4276293516159058
    },
    {
      "filename": "common_voice_ig_30689999.wav",
      "utmos": 1.3354743719100952
    },
    {
      "filename": "common_voice_ig_30690000.wav",
      "utmos": 1.7786784172058105
    },
    {
      "filename": "common_voice_ig_30690001.wav",
      "utmos": 1.6854205131530762
    },
    {
      "filename": "common_voice_ig_30690008.wav",
      "utmos": 1.3750358819961548
    },
    {
      "filename": "common_voice_ig_30690009.wav",
      "utmos": 1.326546549797058
    },
    {
      "filename": "common_voice_ig_30690010.wav",
      "utmos": 1.3271141052246094
    },
    {
      "filename": "common_voice_ig_30690011.wav",
      "utmos": 1.276593804359436
    },
    {
      "filename": "common_voice_ig_30690012.wav",
      "utmos": 1.3252180814743042
    },
    {
      "filename": "common_voice_ig_30690129.wav",
      "utmos": 1.3352354764938354
    },
    {
      "filename": "common_voice_ig_30690130.wav",
      "utmos": 1.3737742900848389
    },
    {
      "filename": "common_voice_ig_30690131.wav",
      "utmos": 1.3004980087280273
    },
    {
      "filename": "common_voice_ig_30690132.wav",
      "utmos": 1.3705021142959595
    },
    {
      "filename": "common_voice_ig_30690133.wav",
      "utmos": 1.33466637134552
    },
    {
      "filename": "common_voice_ig_30690252.wav",
      "utmos": 1.3835101127624512
    },
    {
      "filename": "common_voice_ig_30690253.wav",
      "utmos": 1.380438208580017
    },
    {
      "filename": "common_voice_ig_30690254.wav",
      "utmos": 1.2976086139678955
    },
    {
      "filename": "common_voice_ig_30690255.wav",
      "utmos": 1.4770132303237915
    },
    {
      "filename": "common_voice_ig_30690256.wav",
      "utmos": 1.3173846006393433
    },
    {
      "filename": "common_voice_ig_30690342.wav",
      "utmos": 1.4827125072479248
    },
    {
      "filename": "common_voice_ig_30690343.wav",
      "utmos": 1.250948190689087
    },
    {
      "filename": "common_voice_ig_30690344.wav",
      "utmos": 1.4342434406280518
    },
    {
      "filename": "common_voice_ig_30690345.wav",
      "utmos": 1.3829635381698608
    },
    {
      "filename": "common_voice_ig_30690346.wav",
      "utmos": 1.5549397468566895
    },
    {
      "filename": "common_voice_ig_30690397.wav",
      "utmos": 1.623303771018982
    },
    {
      "filename": "common_voice_ig_30690398.wav",
      "utmos": 1.406079888343811
    },
    {
      "filename": "common_voice_ig_30690399.wav",
      "utmos": 1.6339197158813477
    },
    {
      "filename": "common_voice_ig_30690400.wav",
      "utmos": 1.392065167427063
    },
    {
      "filename": "common_voice_ig_30690401.wav",
      "utmos": 1.6671572923660278
    },
    {
      "filename": "common_voice_ig_30690501.wav",
      "utmos": 1.2816667556762695
    },
    {
      "filename": "common_voice_ig_30690502.wav",
      "utmos": 1.5469540357589722
    },
    {
      "filename": "common_voice_ig_30690503.wav",
      "utmos": 1.2805237770080566
    },
    {
      "filename": "common_voice_ig_30690504.wav",
      "utmos": 1.3795398473739624
    },
    {
      "filename": "common_voice_ig_30690505.wav",
      "utmos": 1.3139568567276
    },
    {
      "filename": "common_voice_ig_30690536.wav",
      "utmos": 1.9567043781280518
    },
    {
      "filename": "common_voice_ig_30690537.wav",
      "utmos": 1.4039863348007202
    },
    {
      "filename": "common_voice_ig_30690538.wav",
      "utmos": 1.3298585414886475
    },
    {
      "filename": "common_voice_ig_30690539.wav",
      "utmos": 1.2848278284072876
    },
    {
      "filename": "common_voice_ig_30690540.wav",
      "utmos": 1.4024670124053955
    },
    {
      "filename": "common_voice_ig_30690541.wav",
      "utmos": 1.9753155708312988
    },
    {
      "filename": "common_voice_ig_30690542.wav",
      "utmos": 1.5806556940078735
    },
    {
      "filename": "common_voice_ig_30690543.wav",
      "utmos": 1.5474523305892944
    },
    {
      "filename": "common_voice_ig_30690544.wav",
      "utmos": 1.7506541013717651
    },
    {
      "filename": "common_voice_ig_30690545.wav",
      "utmos": 1.2754559516906738
    },
    {
      "filename": "common_voice_ig_30690546.wav",
      "utmos": 1.4535472393035889
    },
    {
      "filename": "common_voice_ig_30690547.wav",
      "utmos": 1.3692659139633179
    },
    {
      "filename": "common_voice_ig_30690548.wav",
      "utmos": 1.3313215970993042
    },
    {
      "filename": "common_voice_ig_30690549.wav",
      "utmos": 1.3077149391174316
    },
    {
      "filename": "common_voice_ig_30690566.wav",
      "utmos": 1.369308590888977
    },
    {
      "filename": "common_voice_ig_30690567.wav",
      "utmos": 1.6686803102493286
    },
    {
      "filename": "common_voice_ig_30690568.wav",
      "utmos": 1.3334858417510986
    },
    {
      "filename": "common_voice_ig_30690569.wav",
      "utmos": 1.3561841249465942
    },
    {
      "filename": "common_voice_ig_30690570.wav",
      "utmos": 1.4843685626983643
    },
    {
      "filename": "common_voice_ig_43439374.wav",
      "utmos": 1.2724778652191162
    },
    {
      "filename": "common_voice_ig_43439375.wav",
      "utmos": 1.2780777215957642
    },
    {
      "filename": "common_voice_ig_43439376.wav",
      "utmos": 1.3281781673431396
    },
    {
      "filename": "common_voice_ig_43439377.wav",
      "utmos": 1.3078659772872925
    },
    {
      "filename": "common_voice_ig_43439378.wav",
      "utmos": 1.2882697582244873
    },
    {
      "filename": "common_voice_ig_43439508.wav",
      "utmos": 1.2884931564331055
    },
    {
      "filename": "common_voice_ig_43439514.wav",
      "utmos": 1.3635345697402954
    },
    {
      "filename": "common_voice_ig_43439515.wav",
      "utmos": 1.308135747909546
    },
    {
      "filename": "common_voice_ig_43439516.wav",
      "utmos": 1.319236159324646
    },
    {
      "filename": "common_voice_ig_43439517.wav",
      "utmos": 1.2335519790649414
    },
    {
      "filename": "common_voice_ig_43439592.wav",
      "utmos": 1.2674953937530518
    },
    {
      "filename": "common_voice_ig_43439593.wav",
      "utmos": 1.31425940990448
    },
    {
      "filename": "common_voice_ig_43439594.wav",
      "utmos": 1.3585631847381592
    },
    {
      "filename": "common_voice_ig_43439595.wav",
      "utmos": 1.2988783121109009
    },
    {
      "filename": "common_voice_ig_43439596.wav",
      "utmos": 1.2948161363601685
    },
    {
      "filename": "common_voice_ig_43472503.wav",
      "utmos": 3.1008124351501465
    },
    {
      "filename": "common_voice_ig_43472504.wav",
      "utmos": 1.6024874448776245
    },
    {
      "filename": "common_voice_ig_43472505.wav",
      "utmos": 2.1983859539031982
    },
    {
      "filename": "common_voice_ig_43472506.wav",
      "utmos": 1.9082391262054443
    },
    {
      "filename": "common_voice_ig_43472507.wav",
      "utmos": 2.1181375980377197
    },
    {
      "filename": "common_voice_ig_43488897.wav",
      "utmos": 1.2526909112930298
    }
  ]
}